Metadata-Version: 2.1
Name: scpper
Version: 1.1.5
Summary: Python wrapper for ScpperDB API.
Home-page: https://github.com/skippy-dev/scpper/
Author: MrNereof
Author-email: mrnereof@gmail.com
License: MIT
Keywords: scp,scpper,api
Platform: UNKNOWN
Classifier: Development Status :: 4 - Beta
Classifier: Intended Audience :: Other Audience
Classifier: License :: OSI Approved :: MIT License
Classifier: Operating System :: OS Independent
Classifier: Programming Language :: Python :: 3.8
Classifier: Programming Language :: Python :: 3.9
Requires-Python: >=3.8
